Metadata-Version: 2.1
Name: codeformer-app
Version: 0.0.3
Summary: PyTorch implementation of CodeFormer
Home-page: https://github.com/kadirnar/codeformer-pip
Author: kadirnar
License: S-Lab
Keywords: pytorch,codeformer,face,face-swap,face-swapping,face-swap-pytorch,face-swapping-pytorch
Platform: UNKNOWN
Classifier: Development Status :: 5 - Production/Stable
Classifier: Operating System :: OS Independent
Classifier: Intended Audience :: Developers
Classifier: Intended Audience :: Science/Research
Classifier: Programming Language :: Python :: 3
Classifier: Programming Language :: Python :: 3.7
Classifier: Programming Language :: Python :: 3.8
Classifier: Programming Language :: Python :: 3.9
Classifier: Topic :: Software Development :: Libraries
Classifier: Topic :: Software Development :: Libraries :: Python Modules
Classifier: Topic :: Education
Classifier: Topic :: Scientific/Engineering
Classifier: Topic :: Scientific/Engineering :: Artificial Intelligence
Requires-Python: >=3.6
License-File: LICENSE
